pals/BaseElement.py
pals/BeamLine.py
pals/Drift.py
pals/MagneticMultipoleParameters.py
pals/Quadrupole.py
pals/ThickElement.py
pals/__init__.py
pals_schema-0.2.0.dist-info/licenses/LICENSE.txt
pals_schema-0.2.0.dist-info/METADATA
pals_schema-0.2.0.dist-info/WHEEL
pals_schema-0.2.0.dist-info/top_level.txt
pals_schema-0.2.0.dist-info/RECORD
