Metadata-Version: 2.4
Name: pals_schema
Version: 0.2.0
Summary: Python implementation for the Particle Accelerator Lattice Standard (PALS)
Author-email: Axel Huebl <axelhuebl@lbl.gov>, Edoardo Zoni <ezoni@lbl.gov>
Maintainer-email: Axel Huebl <axelhuebl@lbl.gov>, Edoardo Zoni <ezoni@lbl.gov>
License-Expression: BSD-3-Clause-LBNL
Project-URL: Documentation, https://pals-project.readthedocs.io
Project-URL: Repository, https://github.com/campa-consortium/pals-python
Project-URL: Issues, https://github.com/campa-consortium/pals-python/issues
Classifier: Development Status :: 5 - Production/Stable
Classifier: Framework :: Pydantic :: 2
Classifier: Intended Audience :: Developers
Classifier: Intended Audience :: Science/Research
Classifier: Natural Language :: English
Classifier: Programming Language :: Python :: 3
Classifier: Programming Language :: Python :: 3.9
Classifier: Programming Language :: Python :: 3.10
Classifier: Programming Language :: Python :: 3.11
Classifier: Programming Language :: Python :: 3.12
Classifier: Programming Language :: Python :: 3.13
Classifier: Operating System :: OS Independent
Classifier: Topic :: Scientific/Engineering
Classifier: Topic :: Software Development
Requires-Python: >=3.9
License-File: LICENSE.txt
Requires-Dist: pydantic
Requires-Dist: pyyaml
Requires-Dist: toml
Provides-Extra: test
Requires-Dist: pytest; extra == "test"
Dynamic: license-file
